speedybot/__init__.py
speedybot/cards.py
speedybot/cli.py
speedybot/speedybot.py
speedybot_loco-0.1.1.dist-info/METADATA
speedybot_loco-0.1.1.dist-info/WHEEL
speedybot_loco-0.1.1.dist-info/entry_points.txt
speedybot_loco-0.1.1.dist-info/top_level.txt
speedybot_loco-0.1.1.dist-info/RECORD
