Metadata-Version: 2.1
Name: speedybot-loco
Version: 0.1.1
Summary: Use googles-- highly experimental conversation design infra
Home-page: https://github.com/valgaze/speedybot-loco
Author: Victor Algaze
Author-email: valgaze@gmail.com
Classifier: Programming Language :: Python :: 3
Classifier: License :: OSI Approved :: MIT License
Classifier: Operating System :: OS Independent
Requires-Python: >=3.6
Requires-Dist: webexteamssdk ==1.7
Requires-Dist: python-dotenv ==1.0.1
